Metadata-Version: 2.1
Name: example-pkg-sdcev-pd-columns
Version: 0.0.2
Summary: schooldevops sample lib
Home-page: https://github.com/schooldevops/python-tutorials
Author: Schooldevops
Author-email: schooldevops@gmail.com
License: UNKNOWN
Project-URL: Bug Tracker, https://github.com/schooldevops/python-tutorials/issues
Platform: UNKNOWN
Classifier: Programming Language :: Python :: 3
Classifier: License :: OSI Approved :: MIT License
Classifier: Operating System :: OS Independent
Requires-Python: >=3.6
License-File: LICENSE.txt
